<?xml version="1.0" encoding="UTF-8"?>

<!DOCTYPE mapper 
	PUBLIC "-//mybatis.org//DTD Mapper 3.0//EN"
	"http://mybatis.org/dtd/mybatis-3-mapper.dtd">
 
 <mapper namespace="com.edu.springboot.jdbc.IReviewService">
 
 
	<insert id="reviewWrite" >
		INSERT INTO REVIEW 
		(idx, product_idx, bot_cate_idx, member_idx, goods_title, ccomment, star_rate, servey1, servey2, servey3, summary)
		VALUES  
		(REVIEW_seq.nextval, 2, 2, 2, #{goods_title}, #{ccomment}, #{star_rate}, #{servey1}, #{servey2}, #{servey3}, #{summary})
	</insert>

	<select id="reviewView" resultType="com.edu.springboot.jdbc.ReviewDTO"
		parameterType="com.edu.springboot.jdbc.ReviewDTO">
		SELECT * FROM review WHERE idx=#{idx}
		AND goods_title=#{goods_title}
	</select>
 
 
 	<select id="starcount" resultType="com.edu.springboot.jdbc.ReviewDTO">
        SELECT ROUND(AVG(star_rate),1) star_rate
        ,COUNT(goods_title) goods_title
        ,COUNT(CASE WHEN star_rate=1 THEN 1 END) star_rate1
        ,COUNT(CASE WHEN star_rate=2 THEN 1 END) star_rate2
        ,COUNT(CASE WHEN star_rate=3 THEN 1 END) star_rate3
        ,COUNT(CASE WHEN star_rate=4 THEN 1 END) star_rate4
        ,COUNT(CASE WHEN star_rate=5 THEN 1 END) star_rate5
        ,COUNT(CASE WHEN servey1=1 THEN 1 END) servey1_1
        ,COUNT(CASE WHEN servey1=2 THEN 1 END) servey1_2
        ,COUNT(CASE WHEN servey1=3 THEN 1 END) servey1_3
        ,COUNT(CASE WHEN servey2=1 THEN 1 END) servey2_1
        ,COUNT(CASE WHEN servey2=2 THEN 1 END) servey2_2
        ,COUNT(CASE WHEN servey2=3 THEN 1 END) servey2_3
        ,COUNT(CASE WHEN servey3=1 THEN 1 END) servey3_1
        ,COUNT(CASE WHEN servey3=2 THEN 1 END) servey3_2
        ,COUNT(CASE WHEN servey3=3 THEN 1 END) servey3_3
		FROM REVIEW ORDER BY idx desc
 	</select>
 	<select id="starDTO" resultType="com.edu.springboot.jdbc.ReviewDTO">
        SELECT ROUND(AVG(star_rate),1) star_rate
        ,COUNT(goods_title) goods_title
        ,COUNT(CASE WHEN star_rate=1 THEN 1 END) star_rate1
        ,COUNT(CASE WHEN star_rate=2 THEN 1 END) star_rate2
        ,COUNT(CASE WHEN star_rate=3 THEN 1 END) star_rate3
        ,COUNT(CASE WHEN star_rate=4 THEN 1 END) star_rate4
        ,COUNT(CASE WHEN star_rate=5 THEN 1 END) star_rate5
        ,COUNT(CASE WHEN servey1=1 THEN 1 END) servey1_1
        ,COUNT(CASE WHEN servey1=2 THEN 1 END) servey1_2
        ,COUNT(CASE WHEN servey1=3 THEN 1 END) servey1_3
        ,COUNT(CASE WHEN servey2=1 THEN 1 END) servey2_1
        ,COUNT(CASE WHEN servey2=2 THEN 1 END) servey2_2
        ,COUNT(CASE WHEN servey2=3 THEN 1 END) servey2_3
        ,COUNT(CASE WHEN servey3=1 THEN 1 END) servey3_1
        ,COUNT(CASE WHEN servey3=2 THEN 1 END) servey3_2
        ,COUNT(CASE WHEN servey3=3 THEN 1 END) servey3_3
		FROM REVIEW ORDER BY idx desc
 	</select>
 
	<select id="reviewcount" resultType="int">
		SELECT COUNT(*) from review
		<if test="search_word!=null and !search_word.equals('')">
			WHERE ${searchField} like '%'||#{search_word}||'%'
		</if>
	</select>

	<select id="reviewList" resultType="com.edu.springboot.jdbc.ReviewDTO">
		SELECT * FROM review order by idx desc
		<if test="search_word!=null and !search_word.equals('')">
			WHERE ${searchField} like '%'||#{search_word}||'%'
		</if>
	</select>
 </mapper>